Aufgabe 3_ampel/ampelsteuerung.vhdl
library ieee;
use ieee.std_logic_1164.all;
USE IEEE.numeric_std.ALL;

entity ampelsteuerung is 
port(
	clk, reset: in std_logic :='0';
	output_hauptampel_gruen: out std_logic:='0';
	output_hauptampel_rot: out std_logic:='0';
	output_hauptampel_gelb: out std_logic:='0';
	output_nebenampel_gruen: out std_logic:='0';
	output_nebenampel_rot: out std_logic:='0';
	output_nebenampel_gelb: out std_logic:='0'
	);
end ampelsteuerung;

architecture behave of ampelsteuerung is
SIGNAL counter :unsigned (3 downto 0):= "0000"; 

BEGIN
   PROCESS (clk, reset)                                 -- Process der Zähler
   BEGIN
		IF rising_edge(clk) THEN
		counter <= counter +1;
		IF(counter = "0000") THEN
		output_hauptampel_gruen <= '1';
		output_hauptampel_rot <= '0';
		output_hauptampel_gelb <= '0';
		output_nebenampel_gruen <= '0';
		output_nebenampel_rot <= '1';
		output_nebenampel_gelb <= '0';
		
        ELSIF(counter = "0001") THEN
		output_hauptampel_gruen <= '1';
		output_hauptampel_rot <= '0';
		output_hauptampel_gelb <= '0';
		output_nebenampel_gruen <= '0';
		output_nebenampel_rot <= '1';
		output_nebenampel_gelb <= '0';
		
		ELSIF(counter = "0010") THEN
		output_hauptampel_gruen <= '1';
		output_hauptampel_rot <= '0';
		output_hauptampel_gelb <= '0';
		output_nebenampel_gruen <= '0';
		output_nebenampel_rot <= '1';
		output_nebenampel_gelb <= '0';
		
		ELSIF(counter = "0011") THEN
		output_hauptampel_gruen <= '1';
		output_hauptampel_rot <= '0';
		output_hauptampel_gelb <= '0';
		output_nebenampel_gruen <= '0';
		output_nebenampel_rot <= '1';
		output_nebenampel_gelb <= '0';
		
		ELSIF(counter = "0100") THEN
		output_hauptampel_gruen <= '1';
		output_hauptampel_rot <= '0';
		output_hauptampel_gelb <= '0';
		output_nebenampel_gruen <= '0';
		output_nebenampel_rot <= '1';
		output_nebenampel_gelb <= '0';
		
		ELSIF(counter = "0101") THEN
		output_hauptampel_gruen <= '1';
		output_hauptampel_rot <= '0';
		output_hauptampel_gelb <= '0';
		output_nebenampel_gruen <= '0';
		output_nebenampel_rot <= '1';
		output_nebenampel_gelb <= '0';
		
		ELSIF(counter = "0110") THEN
		output_hauptampel_gruen <= '1';
		output_hauptampel_rot <= '0';
		output_hauptampel_gelb <= '0';
		output_nebenampel_gruen <= '0';
		output_nebenampel_rot <= '1';
		output_nebenampel_gelb <= '0';
		
		ELSIF(counter = "0111") THEN
		output_hauptampel_gruen <= '0';
		output_hauptampel_rot <= '0';
		output_hauptampel_gelb <= '1';
		output_nebenampel_gruen <= '0';
		output_nebenampel_rot <= '1';
		output_nebenampel_gelb <= '0';
		
		ELSIF(counter = "1000") THEN
		output_hauptampel_gruen <= '0';
		output_hauptampel_rot <= '1';
		output_hauptampel_gelb <= '0';
		output_nebenampel_gruen <= '0';
		output_nebenampel_rot <= '1';
		output_nebenampel_gelb <= '0';
		
		ELSIF(counter = "1001") THEN
		output_hauptampel_gruen <= '0';
		output_hauptampel_rot <= '1';
		output_hauptampel_gelb <= '0';
		output_nebenampel_gruen <= '0';
		output_nebenampel_rot <= '1';
		output_nebenampel_gelb <= '1';
		
		ELSIF(counter = "1010") THEN
		output_hauptampel_gruen <= '0';
		output_hauptampel_rot <= '1';
		output_hauptampel_gelb <= '0';
		output_nebenampel_gruen <= '1';
		output_nebenampel_rot <= '0';
		output_nebenampel_gelb <= '0';
	
		ELSIF(counter = "1011") THEN
		output_hauptampel_gruen <= '0';
		output_hauptampel_rot <= '1';
		output_hauptampel_gelb <= '0';
		output_nebenampel_gruen <= '1';
		output_nebenampel_rot <= '0';
		output_nebenampel_gelb <= '0';
		
		ELSIF(counter = "1100") THEN
		output_hauptampel_gruen <= '0';
		output_hauptampel_rot <= '1';
		output_hauptampel_gelb <= '0';
		output_nebenampel_gruen <= '1';
		output_nebenampel_rot <= '0';
		output_nebenampel_gelb <= '0';
		ELSIF(counter = "1101") THEN
		output_hauptampel_gruen <= '0';
		output_hauptampel_rot <= '1';
		output_hauptampel_gelb <= '0';
		output_nebenampel_gruen <= '0';
		output_nebenampel_rot <= '0';
		output_nebenampel_gelb <= '1';
		ELSIF(counter = "1110") THEN
		output_hauptampel_gruen <= '0';
		output_hauptampel_rot <= '1';
		output_hauptampel_gelb <= '0';
		output_nebenampel_gruen <= '0';
		output_nebenampel_rot <= '1';
		output_nebenampel_gelb <= '0';
		ELSIF(counter = "1111") THEN
		output_hauptampel_gruen <= '0';
		output_hauptampel_rot <= '1';
		output_hauptampel_gelb <= '1';
		output_nebenampel_gruen <= '0';
		output_nebenampel_rot <= '1';
		output_nebenampel_gelb <= '0';
		counter <= counter +1;
		END IF;
      END IF;
   END PROCESS;

end behave;

Aufgabe 3_ampel/ampelsteuerung_tb.vhdl
library ieee;
use ieee.std_logic_1164.all;

entity ampelsteuerung_tb is 
end ampelsteuerung_tb;

architecture behave of ampelsteuerung_tb is

component ampelsteuerung
port(
	clk, reset: in std_logic := '0';
	output_hauptampel_gruen: out std_logic:= '0';
	output_hauptampel_rot: out std_logic:= '0';
	output_hauptampel_gelb: out std_logic:= '0';
	output_nebenampel_gruen: out std_logic:= '0';
	output_nebenampel_rot: out std_logic:= '0';
	output_nebenampel_gelb: out std_logic:= '0'
	);
end component;

signal clk, reset: std_logic := '0';
signal output_hauptampel_gruen: std_logic := '0';
signal output_hauptampel_rot: std_logic := '0';
signal output_hauptampel_gelb: std_logic := '0';
signal output_nebenampel_gruen: std_logic := '0';
signal output_nebenampel_rot: std_logic := '0';
signal output_nebenampel_gelb: std_logic := '0';
begin

ampel: ampelsteuerung port map(clk => clk, reset=>reset, output_hauptampel_gruen => output_hauptampel_gruen, output_hauptampel_rot => output_hauptampel_rot, output_hauptampel_gelb => output_hauptampel_gelb, output_nebenampel_gruen => output_nebenampel_gruen, output_nebenampel_rot => output_nebenampel_rot, output_nebenampel_gelb => output_nebenampel_gelb);

	process begin
		
		clk<= '1';
		FOR i IN 0 TO 64 LOOP
		
		IF (clk ='1') THEN
		wait for 500000000 ns;
		clk<= '0';
		ELSIF (clk ='0') THEN
		wait for 500000000 ns;
		clk<= '1';
		END IF;

		END LOOP;

		assert false report "Reached end of test";
		wait;
		
	end process;
end behave;

Aufgabe 3_ampel/ampelsteuerung.vcd
$date
  Mon May 11 18:43:04 2020
$end
$version
  GHDL v0
$end
$timescale
  1 fs
$end
$scope module standard $end
$upscope $end
$scope module std_logic_1164 $end
$upscope $end
$scope module numeric_std $end
$upscope $end
$scope module ampelsteuerung_tb $end
$var reg 1 ! clk $end
$var reg 1 " reset $end
$var reg 1 # output_hauptampel_gruen $end
$var reg 1 $ output_hauptampel_rot $end
$var reg 1 % output_hauptampel_gelb $end
$var reg 1 & output_nebenampel_gruen $end
$var reg 1 ' output_nebenampel_rot $end
$var reg 1 ( output_nebenampel_gelb $end
$scope module ampel $end
$var reg 1 ) clk $end
$var reg 1 * reset $end
$var reg 1 + output_hauptampel_gruen $end
$var reg 1 , output_hauptampel_rot $end
$var reg 1 - output_hauptampel_gelb $end
$var reg 1 . output_nebenampel_gruen $end
$var reg 1 / output_nebenampel_rot $end
$var reg 1 0 output_nebenampel_gelb $end
$var reg 4 1 counter[3:0] $end
$upscope $end
$upscope $end
$enddefinitions $end
#0
1!
0"
1#
0$
0%
0&
1'
0(
1)
0*
1+
0,
0-
0.
1/
00
b0001 1
#2000000000000000
0!
0)
#4000000000000000
1!
1)
b0010 1
#6000000000000000
0!
0)
#8000000000000000
1!
1)
b0011 1
#10000000000000000
0!
0)
#12000000000000000
1!
1)
b0100 1
#14000000000000000
0!
0)
#16000000000000000
1!
1)
b0101 1
#18000000000000000
0!
0)
#20000000000000000
1!
1)
b0110 1
#22000000000000000
0!
0)
#24000000000000000
1!
1)
b0111 1
#26000000000000000
0!
0)
#28000000000000000
1!
0#
1%
1)
0+
1-
b1000 1
