Aufgabe 8_alu/alu.vhdl
library ieee;
use ieee.std_logic_1164.all;
USE IEEE.numeric_std.ALL;


entity alu is 
port(
	SEL: in std_logic_vector(3 downto 0);
	INP_A: in signed (3 downto 0);
	INP_B: in signed (3 downto 0);
	OUT_ALU: out signed (3 downto 0)
	);
end alu;

architecture behave of alu is
BEGIN
   PROCESS (SEL, INP_A , INP_B)                               
   BEGIN
	case SEL is
	when "0000" =>
	OUT_ALU <= INP_A + INP_B;
	when "0001" =>
	OUT_ALU <= INP_A - INP_B;
	when "0010" =>
	OUT_ALU <= INP_A + 1;
	when "0011" =>
	OUT_ALU <= INP_A - 1;
	when "0100" =>
	OUT_ALU <= INP_A and INP_B;
	when "0101" =>
	OUT_ALU <= INP_A or INP_B;
	when "0110" =>
	OUT_ALU <= not INP_A;
	when "0111" =>
	OUT_ALU <= INP_A xor INP_B;
	when others => 
	OUT_ALU <= INP_A + INP_B;
	end case;
   END PROCESS;
end behave;

Aufgabe 6_systolische_arrays/systolisches_array_tb.vhdl
library ieee;
use ieee.std_logic_1164.all;
USE IEEE.numeric_std.ALL;

entity alu_tb is 
end alu_tb;

architecture behave of alu_tb is

component alu
port(
	SEL: in std_logic_vector(3 downto 0);
	INP_A: in signed (3 downto 0);
	INP_B: in signed (3 downto 0);
	OUT_ALU: out signed (3 downto 0)
	);
end component;

signal SEL: std_logic_vector(3 downto 0) := (others => '0');
signal INP_A: signed (3 downto 0) := (others => '0');
signal INP_B: signed (3 downto 0) := (others => '0');
signal OUT_ALU: signed (3 downto 0);
begin

alutest: alu port map(SEL => SEL, INP_A => INP_A, INP_B => INP_B, OUT_ALU => OUT_ALU);

	process begin
		INP_A <= "0001";
		INP_B <= "0100";

		SEL <= "0000";
		wait for 1 ns;
		SEL <= "0001";
		wait for 1 ns;
		SEL <= "0010";
		wait for 1 ns;
		SEL <= "0011";
		wait for 1 ns;
		SEL <= "0100";
		wait for 1 ns;
		SEL <= "0101";
		wait for 1 ns;
		SEL <= "0110";
		wait for 1 ns;
		SEL <= "0111";
		wait for 1 ns;

		assert false report "Reached end of test";
		wait;
		
	end process;
end behave;

Aufgabe 8_alu/alu.vcd
$date
  Tue May 19 12:09:18 2020
$end
$version
  GHDL v0
$end
$timescale
  1 fs
$end
$scope module standard $end
$upscope $end
$scope module std_logic_1164 $end
$upscope $end
$scope module numeric_std $end
$upscope $end
$scope module alu_tb $end
$var reg 4 ! sel[3:0] $end
$var reg 4 " inp_a[3:0] $end
$var reg 4 # inp_b[3:0] $end
$var reg 4 $ out_alu[3:0] $end
$scope module alutest $end
$var reg 4 % sel[3:0] $end
$var reg 4 & inp_a[3:0] $end
$var reg 4 ' inp_b[3:0] $end
$var reg 4 ( out_alu[3:0] $end
$upscope $end
$upscope $end
$enddefinitions $end
#0
b0000 !
b0001 "
b0100 #
b0101 $
b0000 %
b0001 &
b0100 '
b0101 (
#1000000
b0001 !
b1101 $
b0001 %
b1101 (
#2000000
b0010 !
b0010 $
b0010 %
b0010 (
#3000000
b0011 !
b0000 $
b0011 %
b0000 (
#4000000
b0100 !
b0100 %
#5000000
b0101 !
b0101 $
b0101 %
b0101 (
#6000000
b0110 !
b1110 $
b0110 %
b1110 (
#7000000
b0111 !
b0101 $
b0111 %
b0101 (
